patreon/__init__.py
patreon/api.py
patreon/api_spec.py
patreon/oauth.py
patreon/oauth_spec.py
patreon/utils.py
patreon/jsonapi/__init__.py
patreon/jsonapi/parser.py
patreon/jsonapi/parser_spec.py
patreon/jsonapi/url_util.py
patreon/jsonapi/url_util_spec.py
patreon/schemas/__init__.py
patreon/schemas/address.py
patreon/schemas/address_spec.py
patreon/schemas/benefit.py
patreon/schemas/benefit_spec.py
patreon/schemas/campaign.py
patreon/schemas/campaign_spec.py
patreon/schemas/deliverable.py
patreon/schemas/deliverable_spec.py
patreon/schemas/goal.py
patreon/schemas/goal_spec.py
patreon/schemas/media.py
patreon/schemas/media_spec.py
patreon/schemas/member.py
patreon/schemas/member_spec.py
patreon/schemas/oauthclient.py
patreon/schemas/oauthclient_spec.py
patreon/schemas/tier.py
patreon/schemas/tier_spec.py
patreon/schemas/user.py
patreon/schemas/user_spec.py
patreon/schemas/webhook.py
patreon/schemas/webhook_spec.py
patreon/version_compatibility/__init__.py
patreon/version_compatibility/utc_timezone.py
patreon/version_compatibility/utc_timezone_spec.py
patreon_v2-0.5.1.dist-info/licenses/LICENSE
patreon_v2-0.5.1.dist-info/licenses/NOTICE
patreon_v2-0.5.1.dist-info/METADATA
patreon_v2-0.5.1.dist-info/WHEEL
patreon_v2-0.5.1.dist-info/top_level.txt
patreon_v2-0.5.1.dist-info/RECORD
