Metadata-Version: 2.4
Name: patreon-v2
Version: 0.5.1
Summary: Python library for interacting with the Patreon API. OAuth-centric for now.
Author-email: Welt Studio <dev@welt-studio.com>
Maintainer-email: Welt Studio <dev@welt-studio.com>
License: Apache-2.0
Project-URL: Homepage, https://github.com/Welt-Studio-Desenvolvimentos-LTDA/patreon-python
Project-URL: Bug Reports, https://github.com/Welt-Studio-Desenvolvimentos-LTDA/patreon-python/issues
Project-URL: Source, https://github.com/Welt-Studio-Desenvolvimentos-LTDA/patreon-python
Keywords: patreon,api,oauth,python
Classifier: Development Status :: 5 - Production/Stable
Classifier: Intended Audience :: Developers
Classifier: Operating System :: OS Independent
Classifier: Programming Language :: Python :: 3
Classifier: Programming Language :: Python :: 3 :: Only
Classifier: Programming Language :: Python :: 3.8
Classifier: Programming Language :: Python :: 3.9
Classifier: Programming Language :: Python :: 3.10
Classifier: Programming Language :: Python :: 3.11
Classifier: Programming Language :: Python :: 3.12
Requires-Python: >=3.8
License-File: LICENSE
License-File: NOTICE
Requires-Dist: requests>=2.28
Requires-Dist: six>=1.16.0
Requires-Dist: setuptools
Provides-Extra: dev
Requires-Dist: pytest; extra == "dev"
Requires-Dist: pytest-cov; extra == "dev"
Requires-Dist: mock; extra == "dev"
Dynamic: license-file
